src/__init__.py
src/abstract.py
src/decorator.py
src/geometry/__init__.py
src/geometry/coefficient_base.py
src/geometry/polynomial1d.py
src/geometry/polynomial2d.py
src/geometry/spline1d.py
src/geometry/spline2d.py
src/solver/__init__.py
src/solver/distance_time_solver.py
src/solver/path_solver.py
src/solver/solver_impl.py
src/solver/spline_nd_solver.py
test/__init__.py
test/geometry/__init__.py
test/geometry/test_1d_polynomial.py
test/geometry/test_1d_spline.py
test/geometry/test_2d_polynomial.py
test/geometry/test_2d_spline.py
test/solver/__init__.py
test/solver/test_distance_time_solver.py
test/solver/test_path_solver.py
test/solver/test_solver_impl.py
test/solver/test_spline_nd_solver.py
drivepathsolver-0.1.2.dist-info/METADATA
drivepathsolver-0.1.2.dist-info/WHEEL
drivepathsolver-0.1.2.dist-info/top_level.txt
drivepathsolver-0.1.2.dist-info/RECORD
